README.md
setup.cfg
setup.py
nba_scraper/__init__.py
nba_scraper/helper_functions.py
nba_scraper/nba_scraper.py
nba_scraper/scrape_functions.py
nba_scraper/stat_calc_functions.py
nba_scraper/wnba_scrape_functions.py
nba_scraper.egg-info/PKG-INFO
nba_scraper.egg-info/SOURCES.txt
nba_scraper.egg-info/dependency_links.txt
nba_scraper.egg-info/requires.txt
nba_scraper.egg-info/top_level.txt