Metadata-Version: 2.1
Name: nba-scraper
Version: 1.0.7
Summary: A Python package to scrape the NBA api and return a play by play file
Home-page: https://github.com/mcbarlowe/nba_scraper
Author: Matthew Barlowe
Author-email: matt@barloweanalytics.com
License: GNU General Public License v3.0
Download-URL: https://github.com/mcbarlowe/nba_scraper/archive/v1.0.7.tar.gz
Keywords: basketball,NBA,scraper
Platform: UNKNOWN
Classifier: Development Status :: 3 - Alpha
Classifier: Intended Audience :: Science/Research
Classifier: Topic :: Software Development :: Build Tools
Classifier: License :: OSI Approved :: GNU General Public License v3 (GPLv3)
Classifier: Programming Language :: Python :: 3.6
